intent_suggestions/__init__.py
intent_suggestions/model.py
intent_suggestions-0.1.0.dist-info/LICENSE
intent_suggestions-0.1.0.dist-info/METADATA
intent_suggestions-0.1.0.dist-info/WHEEL
intent_suggestions-0.1.0.dist-info/top_level.txt
intent_suggestions-0.1.0.dist-info/RECORD
