Metadata-Version: 2.1
Name: intent-suggestions
Version: 0.1.0
Summary: Early intent detection using n-gram language models
Author: Ivan Kunyankin
License: MIT License        
Project-URL: Homepage, https://github.com/ivankunyankin/intent_suggestions
Classifier: Programming Language :: Python :: 3
Classifier: License :: OSI Approved :: MIT License
Classifier: Operating System :: OS Independent
Requires-Python: >=3.7
License-File: LICENSE
